MANIFEST.in
README.rst
setup.py
docs/__init__.py
docs/conf.py
s3filesmanager/__init__.py
s3filesmanager/admin.py
s3filesmanager/models.py
s3filesmanager/settings.py
s3filesmanager/tests.py
s3filesmanager/urls.py
s3filesmanager/utils.py
s3filesmanager/views.py
s3filesmanager.egg-info/PKG-INFO
s3filesmanager.egg-info/SOURCES.txt
s3filesmanager.egg-info/dependency_links.txt
s3filesmanager.egg-info/not-zip-safe
s3filesmanager.egg-info/requires.txt
s3filesmanager.egg-info/top_level.txt
s3filesmanager/migrations/0001_initial.py
s3filesmanager/migrations/__init__.py
s3filesmanager/static/img/80x80.png
s3filesmanager/static/js/jquery-latest.js
s3filesmanager/static/js/jquery.cookie.js
s3filesmanager/static/js/underscore.js
s3filesmanager/static/js/plupload/plupload.browserplus.js
s3filesmanager/static/js/plupload/plupload.flash.js
s3filesmanager/static/js/plupload/plupload.flash.swf
s3filesmanager/static/js/plupload/plupload.full.js
s3filesmanager/static/js/plupload/plupload.gears.js
s3filesmanager/static/js/plupload/plupload.html4.js
s3filesmanager/static/js/plupload/plupload.html5.js
s3filesmanager/static/js/plupload/plupload.js
s3filesmanager/static/js/plupload/plupload.silverlight.js
s3filesmanager/static/js/plupload/plupload.silverlight.xap
s3filesmanager/static/js/plupload/i18n/cs.js
s3filesmanager/static/js/plupload/i18n/da.js
s3filesmanager/static/js/plupload/i18n/de.js
s3filesmanager/static/js/plupload/i18n/el.js
s3filesmanager/static/js/plupload/i18n/es.js
s3filesmanager/static/js/plupload/i18n/et.js
s3filesmanager/static/js/plupload/i18n/fa.js
s3filesmanager/static/js/plupload/i18n/fi.js
s3filesmanager/static/js/plupload/i18n/fr-ca.js
s3filesmanager/static/js/plupload/i18n/fr.js
s3filesmanager/static/js/plupload/i18n/hr.js
s3filesmanager/static/js/plupload/i18n/hu.js
s3filesmanager/static/js/plupload/i18n/it.js
s3filesmanager/static/js/plupload/i18n/ja.js
s3filesmanager/static/js/plupload/i18n/ko.js
s3filesmanager/static/js/plupload/i18n/lv.js
s3filesmanager/static/js/plupload/i18n/nl.js
s3filesmanager/static/js/plupload/i18n/pl.js
s3filesmanager/static/js/plupload/i18n/pt-br.js
s3filesmanager/static/js/plupload/i18n/ro.js
s3filesmanager/static/js/plupload/i18n/ru.js
